kpush/__init__.py
kpush-0.1.1.dist-info/METADATA
kpush-0.1.1.dist-info/WHEEL
kpush-0.1.1.dist-info/top_level.txt
kpush-0.1.1.dist-info/RECORD
