Metadata-Version: 2.1
Name: kpush
Version: 0.1.1
Summary: kpush client api
Home-page: https://github.com/dantezhu/kpush
Author: dantezhu
Author-email: dantezhu <dantezhu@qq.com>
License: MIT
Project-URL: Homepage, https://github.com/dantezhu/kpush
Requires-Dist: requests
